termstyles/__init__.py
termstyles-0.0.2.dist-info/METADATA
termstyles-0.0.2.dist-info/WHEEL
termstyles-0.0.2.dist-info/top_level.txt
termstyles-0.0.2.dist-info/RECORD
