Metadata-Version: 2.1
Name: termstyles
Version: 0.0.2
Summary: Simple terminal coloring module
Author: N0NL0C4L
Author-email: <n0nl0c4l@gmail.com>
Keywords: python,color,termstyles,terminal,console
Classifier: Programming Language :: Python :: 3
Classifier: Operating System :: Unix
Classifier: Operating System :: MacOS :: MacOS X
Classifier: Operating System :: Microsoft :: Windows
